README.md
setup.py
PyUniversalKit/__init__.py
PyUniversalKit/version.py
PyUniversalKit.egg-info/PKG-INFO
PyUniversalKit.egg-info/SOURCES.txt
PyUniversalKit.egg-info/dependency_links.txt
PyUniversalKit.egg-info/requires.txt
PyUniversalKit.egg-info/top_level.txt
PyUniversalKit/AnswerSearchkit/__init__.py
PyUniversalKit/AnswerSearchkit/admin.py
PyUniversalKit/AnswerSearchkit/api.py
PyUniversalKit/AnswerSearchkit/error.py
PyUniversalKit/AnswerSearchkit/operate.py
PyUniversalKit/AnswerSearchkit/API/__init__.py
PyUniversalKit/AnswerSearchkit/API/icodef.py
PyUniversalKit/AnswerSearchkit/CookieManager/__init__.py
PyUniversalKit/AnswerSearchkit/CookieManager/api.py
PyUniversalKit/AnswerSearchkit/Manage/__init__.py
PyUniversalKit/AnswerSearchkit/Manage/api.py
PyUniversalKit/AnswerSearchkit/Models/AnswerObject.py
PyUniversalKit/AnswerSearchkit/Models/CheckObject.py
PyUniversalKit/AnswerSearchkit/Models/__init__.py
PyUniversalKit/AnswerSearchkit/Structs/Mapping.py
PyUniversalKit/AnswerSearchkit/Structs/Matches.py
PyUniversalKit/AnswerSearchkit/Structs/__init__.py
PyUniversalKit/CSVkit/__init__.py
PyUniversalKit/CSVkit/api.py
PyUniversalKit/CSVkit/error.py
PyUniversalKit/CSVkit/models.py
PyUniversalKit/CSVkit/operate.py
PyUniversalKit/Netkit/USER_AGENT_LIST.py
PyUniversalKit/Netkit/__init__.py
PyUniversalKit/Netkit/api.py
PyUniversalKit/Netkit/models.py
PyUniversalKit/Netkit/proxy.py
PyUniversalKit/Netkit/test.py