Metadata-Version: 2.1
Name: PyUniversalKit
Version: 1.1.1
Summary: Hello,PyUniversalKit!
Home-page: https://github.com/yangtang-special/PyUniversalKit/tree/formal
Author: MatthewYt
Author-email: 2158707744@qq.com
License: UNKNOWN
Platform: UNKNOWN
